qqmusicbox/__init__.py
qqmusicbox/__main__.py
qqmusicbox/__version__.py
qqmusicbox/api.py
qqmusicbox/cache.py
qqmusicbox/config.py
qqmusicbox/const.py
qqmusicbox/logger.py
qqmusicbox/menu.py
qqmusicbox/osdlyrics.py
qqmusicbox/player.py
qqmusicbox/scrollstring.py
qqmusicbox/singleton.py
qqmusicbox/storage.py
qqmusicbox/terminalsize.py
qqmusicbox/ui.py
qqmusicbox/utils.py
qqmusicbox-0.1.1.dist-info/DESCRIPTION.rst
qqmusicbox-0.1.1.dist-info/METADATA
qqmusicbox-0.1.1.dist-info/RECORD
qqmusicbox-0.1.1.dist-info/WHEEL
qqmusicbox-0.1.1.dist-info/entry_points.txt
qqmusicbox-0.1.1.dist-info/metadata.json
qqmusicbox-0.1.1.dist-info/top_level.txt
