Metadata-Version: 2.0
Name: qqmusicbox
Version: 0.1.1
Summary: qq music in commandline
Home-page: https://github.com/lai-bluejay/qqmusicbox
Author: Charles Lai
Author-email: lai.bluejay@gmail.com
License: MIT
Platform: UNKNOWN
Classifier: License :: OSI Approved :: MIT License
Classifier: Programming Language :: Python
Classifier: Programming Language :: Python :: 3
Classifier: Programming Language :: Python :: 3.6
Classifier: Programming Language :: Python :: Implementation :: CPython
Classifier: Programming Language :: Python :: Implementation :: PyPy
Requires-Python: >=3.5.0
Requires-Dist: future
Requires-Dist: pycryptodomex
Requires-Dist: requests
Requires-Dist: requests-cache
